glapi/__init__.py
glapi/configuration.py
glapi/connection.py
glapi/epic.py
glapi/group.py
glapi/issue.py
glapi/project.py
glapi/user.py
glapi-0.7.12.dist-info/METADATA
glapi-0.7.12.dist-info/WHEEL
glapi-0.7.12.dist-info/top_level.txt
glapi-0.7.12.dist-info/RECORD
