Metadata-Version: 2.1
Name: glapi
Version: 0.7.12
Summary: Python package to interact with GitLab API.
Home-page: https://gitlab.com/lgensinger/glapi
Requires-Dist: requests
Provides-Extra: test
Requires-Dist: lorem ; extra == 'test'
Requires-Dist: pkgparser ; extra == 'test'
Requires-Dist: pytest ; extra == 'test'
Requires-Dist: pytest-cov ; extra == 'test'
